qinghe_py_autoprocess/__init__.py
qinghe_py_autoprocess/autoprocess/__init__.py
qinghe_py_autoprocess/autoprocess/auto_process.py
qinghe_py_autoprocess-0.0.3.dist-info/METADATA
qinghe_py_autoprocess-0.0.3.dist-info/WHEEL
qinghe_py_autoprocess-0.0.3.dist-info/entry_points.txt
qinghe_py_autoprocess-0.0.3.dist-info/top_level.txt
qinghe_py_autoprocess-0.0.3.dist-info/RECORD
