Metadata-Version: 2.4
Name: qinghe_py_autoprocess
Version: 0.0.3
Summary: 提取视频音轨并处理倍速进行输出
Author-email: qinghe <2352463068@qq.com>
Requires-Python: >=3.8
Requires-Dist: ffmpeg-python
